README.md
setup.py
uge2slurm/__init__.py
uge2slurm/mapper.py
uge2slurm.egg-info/PKG-INFO
uge2slurm.egg-info/SOURCES.txt
uge2slurm.egg-info/dependency_links.txt
uge2slurm.egg-info/entry_points.txt
uge2slurm.egg-info/top_level.txt
uge2slurm/commands/__init__.py
uge2slurm/commands/argparser.py
uge2slurm/commands/qacct/__init__.py
uge2slurm/commands/qalter/__init__.py
uge2slurm/commands/qconf/__init__.py
uge2slurm/commands/qdel/__init__.py
uge2slurm/commands/qhold/__init__.py
uge2slurm/commands/qhost/__init__.py
uge2slurm/commands/qlogin/__init__.py
uge2slurm/commands/qmake/__init__.py
uge2slurm/commands/qmod/__init__.py
uge2slurm/commands/qmon/__init__.py
uge2slurm/commands/qping/__init__.py
uge2slurm/commands/qquota/__init__.py
uge2slurm/commands/qralter/__init__.py
uge2slurm/commands/qrdel/__init__.py
uge2slurm/commands/qresub/__init__.py
uge2slurm/commands/qrls/__init__.py
uge2slurm/commands/qrsh/__init__.py
uge2slurm/commands/qrstat/__init__.py
uge2slurm/commands/qrsub/__init__.py
uge2slurm/commands/qselect/__init__.py
uge2slurm/commands/qsh/__init__.py
uge2slurm/commands/qstat/__init__.py
uge2slurm/commands/qsub/__init__.py
uge2slurm/commands/qsub/argparser.py
uge2slurm/commands/qsub/mapper.py
uge2slurm/commands/qsub/sinfo.py
uge2slurm/commands/qsub/squeue.py
uge2slurm/commands/uge2slurm/__init__.py
uge2slurm/commands/wrapper/uge2slurm-qsubwrapper.sh
uge2slurm/utils/__init__.py
uge2slurm/utils/color.py
uge2slurm/utils/log.py
uge2slurm/utils/path.py
uge2slurm/utils/slurm.py
uge2slurm/utils/py2/__init__.py
uge2slurm/utils/py2/argparse.py
uge2slurm/utils/py2/functools.py
uge2slurm/utils/py2/os.py
uge2slurm/utils/py2/subprocess.py